vips_abi/__init__.py
vips_abi/abi.py
vips_abi/base.py
vips_abi/codec.py
vips_abi/constants.py
vips_abi/decoding.py
vips_abi/encoding.py
vips_abi/exceptions.py
vips_abi/grammar.py
vips_abi/packed.py
vips_abi/py.typed
vips_abi/registry.py
vips_abi/tools/__init__.py
vips_abi/tools/_strategies.py
vips_abi/utils/__init__.py
vips_abi/utils/numeric.py
vips_abi/utils/padding.py
vips_abi/utils/string.py
vips_abi-2.0.0.dist-info/LICENSE
vips_abi-2.0.0.dist-info/METADATA
vips_abi-2.0.0.dist-info/WHEEL
vips_abi-2.0.0.dist-info/top_level.txt
vips_abi-2.0.0.dist-info/RECORD
